dedomenon/__cli__.py
dedomenon/__init__.py
dedomenon/_version.py
dedomenon/conf/__init__.py
dedomenon/conf/about/__init__.yaml
dedomenon/conf/batch/__init__.yaml
dedomenon/conf/config.yaml
dedomenon/conf/dotenv/__init__.yaml
dedomenon/conf/hconf.yaml
dedomenon/conf/hydra/help/help.yaml
dedomenon/conf/hydra/job_logging/custom.yaml
dedomenon/conf/joblib/__init__.yaml
dedomenon/conf/mode/__init__.yaml
dedomenon/conf/mode/debug.yaml
dedomenon/conf/path/__batch__.yaml
dedomenon/conf/path/__default__.yaml
dedomenon/conf/path/__init__.yaml
dedomenon/conf/project/__init__.yaml
dedomenon/conf/task/__init__.yaml
dedomenon/project.toml
dedomenon/py.typed
dedomenon-0.1.3.dist-info/LICENSE
dedomenon-0.1.3.dist-info/METADATA
dedomenon-0.1.3.dist-info/WHEEL
dedomenon-0.1.3.dist-info/entry_points.txt
dedomenon-0.1.3.dist-info/RECORD
